chaosdatadog/__init__.py
chaosdatadog/metrics/__init__.py
chaosdatadog/metrics/probes.py
chaosdatadog/metrics/utils.py
chaosdatadog/slo/__init__.py
chaosdatadog/slo/probes.py
chaosdatadog/slo/tolerances.py
chaostoolkit_datadog-0.3.1.dist-info/METADATA
chaostoolkit_datadog-0.3.1.dist-info/WHEEL
chaostoolkit_datadog-0.3.1.dist-info/licenses/LICENSE
chaostoolkit_datadog-0.3.1.dist-info/RECORD
