Metadata-Version: 2.1
Name: chaostoolkit-datadog
Version: 0.3.1
Summary: Chaos Toolkit extension for DataDog
Author-Email: Chaos Toolkit <contact@chaostoolkit.org>, Sylvain Hellegouarch <sh@defuze.org>
License: Apache-2.0
Classifier: Development Status :: 4 - Beta
Classifier: Intended Audience :: Developers
Classifier: License :: Freely Distributable
Classifier: License :: OSI Approved :: Apache Software License
Classifier: Operating System :: OS Independent
Classifier: Programming Language :: Python
Classifier: Programming Language :: Python :: 3
Classifier: Programming Language :: Python :: 3.8
Classifier: Programming Language :: Python :: 3.9
Classifier: Programming Language :: Python :: 3.10
Classifier: Programming Language :: Python :: 3.11
Classifier: Programming Language :: Python :: 3.12
Classifier: Programming Language :: Python :: Implementation
Classifier: Programming Language :: Python :: Implementation :: CPython
Project-URL: Homepage, https://chaostoolkit.org/
Project-URL: Documentation, https://chaostoolkit.org/drivers/datadog/
Project-URL: Repository, https://github.com/chaostoolkit-incubator/chaostoolkit-datadog
Project-URL: Changelog, https://github.com/chaostoolkit-incubator/chaostoolkit-datadog/blob/master/CHANGELOG.md
Requires-Python: >=3.8
Requires-Dist: datadog-api-client>=2.24.0
Requires-Dist: chaostoolkit-lib>=1.42.1
Requires-Dist: arrow>=1.3.0
